{
  "publicPath": "/_nuxt/",
  "all": [
    "../server/index.spa.html",
    "../server/index.ssr.html",
    "0d369ea.js",
    "0fc8ade.js",
    "1acdda1.js",
    "1c1d6d6.js",
    "261c78a.js",
    "45f6f75.js",
    "5b75c0b.js",
    "6183672.js",
    "86db296.js",
    "LICENSES",
    "ac6bae7.js",
    "app.aae5950.css",
    "b4bc153.js",
    "c3f605a.js",
    "faa11c8.js",
    "fonts/Karla-Bold.008289c.ttf",
    "fonts/Karla-ExtraBold.deb29ed.ttf",
    "fonts/Karla-ExtraLight.8c255a1.ttf",
    "fonts/Karla-Light.345e34a.ttf",
    "fonts/Karla-Medium.fc3c77c.ttf",
    "fonts/MADE Mirage Regular.155182b.otf",
    "fonts/MADE Mirage Thin.a390820.otf",
    "img/1.a24ef24.png",
    "img/10.5e29cfd.PNG",
    "img/11.38bcc6b.PNG",
    "img/2.48cfa18.png",
    "img/3.58cde61.png",
    "img/4.22c3e2d.png",
    "img/5.7b6c5ae.png",
    "img/6.633fbbc.png",
    "img/7.49dd84e.png",
    "img/8.7f1ecfc.png",
    "img/9.cef6afe.PNG",
    "img/ART.3d13d62.PNG",
    "img/BORE.95c5a8e.jpg",
    "img/Courtney Valentine Spivey (1).33116a9.png",
    "img/Courtney Valentine Spivey (2).3bda1d9.png",
    "img/GODS.823781b.jpg",
    "img/UKIE_GJ.80730d8.jpg",
    "img/bore_horizontal.30dffd2.PNG",
    "img/peacekeeper_gif.e53f329.gif",
    "img/peacekeeper_still.356ed48.png",
    "img/profile.498ed78.jpg",
    "img/site_logo.ab93554.png",
    "pages/about.94d52b4.css",
    "pages/code.cafdae8.css",
    "pages/gameProjects/BORE.f629f95.css",
    "pages/index.decfdd8.css",
    "pages/resume.bbe143b.css",
    "vendors/app.ac76dde.css"
  ],
  "initial": [
    "b4bc153.js",
    "261c78a.js",
    "vendors/app.ac76dde.css",
    "86db296.js",
    "app.aae5950.css",
    "6183672.js"
  ],
  "async": [
    "0d369ea.js",
    "0fc8ade.js",
    "1acdda1.js",
    "1c1d6d6.js",
    "45f6f75.js",
    "5b75c0b.js",
    "ac6bae7.js",
    "c3f605a.js",
    "faa11c8.js",
    "pages/about.94d52b4.css",
    "pages/code.cafdae8.css",
    "pages/gameProjects/BORE.f629f95.css",
    "pages/index.decfdd8.css",
    "pages/resume.bbe143b.css"
  ],
  "modules": {
    "10407679": [
      51,
      10
    ],
    "10776287": [
      6
    ],
    "18398901": [
      6
    ],
    "32479086": [
      51,
      10
    ],
    "34085782": [
      51,
      10
    ],
    "39204846": [
      51,
      10
    ],
    "47865972": [
      51,
      10
    ],
    "50460629": [
      51,
      10
    ],
    "52712981": [
      6
    ],
    "54029800": [
      13,
      9,
      24,
      25,
      26,
      27,
      28,
      29,
      30,
      31,
      32,
      33,
      34,
      42,
      23,
      22,
      17,
      21,
      18,
      20,
      19,
      24,
      25,
      26,
      27,
      28,
      29,
      30,
      31,
      32,
      33,
      34,
      43,
      45
    ],
    "56275579": [
      47,
      5
    ],
    "60044045": [
      51,
      10
    ],
    "62485480": [
      13,
      9,
      24,
      25,
      26,
      27,
      28,
      29,
      30,
      31,
      32,
      33,
      34,
      42,
      23,
      22,
      17,
      21,
      18,
      20,
      19,
      24,
      25,
      26,
      27,
      28,
      29,
      30,
      31,
      32,
      33,
      34,
      43,
      45
    ],
    "62648382": [
      13,
      9,
      24,
      25,
      26,
      27,
      28,
      29,
      30,
      31,
      32,
      33,
      34,
      42,
      23,
      22,
      17,
      21,
      18,
      20,
      19,
      24,
      25,
      26,
      27,
      28,
      29,
      30,
      31,
      32,
      33,
      34,
      43,
      45
    ],
    "69521988": [
      51,
      10
    ],
    "73342729": [
      6
    ],
    "73895066": [
      51,
      10
    ],
    "1f76745e": [
      51,
      10
    ],
    "1fdeda98": [
      6
    ],
    "254dffaa": [
      6
    ],
    "5aed8266": [
      6
    ],
    "d0b50766": [
      6
    ],
    "ee877cb4": [
      6
    ],
    "0a0d10aa": [
      6
    ],
    "6453f970": [
      6
    ],
    "10029ed1": [
      51,
      10
    ],
    "be6ae516": [
      13,
      9,
      24,
      25,
      26,
      27,
      28,
      29,
      30,
      31,
      32,
      33,
      34,
      42,
      23,
      22,
      17,
      21,
      18,
      20,
      19,
      24,
      25,
      26,
      27,
      28,
      29,
      30,
      31,
      32,
      33,
      34,
      43,
      45
    ],
    "df1903fc": [
      6
    ],
    "7ee392f0": [
      6
    ],
    "227e7da4": [
      6
    ],
    "7da3e1b3": [
      6
    ],
    "1eeb397c": [
      6
    ],
    "fd98f2bc": [
      6
    ],
    "7b29b4c1": [
      6
    ],
    "1e2805e6": [
      6
    ],
    "a2e49628": [
      6
    ],
    "47ddc5ae": [
      6
    ],
    "275a5b31": [
      6
    ],
    "2070d355": [
      6
    ],
    "671ef456": [
      6
    ],
    "3fa1d670": [
      6
    ],
    "51cb0b70": [
      6
    ],
    "0b35a57e": [
      6
    ],
    "78cbc4b2": [
      6
    ],
    "335d61f4": [
      6
    ],
    "86205bf6": [
      51,
      10
    ],
    "0d58b937": [
      6
    ],
    "226ae552": [
      6
    ],
    "fd6b0e48": [
      6
    ],
    "2b780644": [
      6
    ],
    "641f7c2c": [
      6
    ],
    "4f9aef8a": [
      6
    ],
    "64c2ee3e": [
      6
    ],
    "f403abc2": [
      6
    ],
    "f1a0b604": [
      6
    ],
    "a38c7e7c": [
      6
    ],
    "30fffb37": [
      6
    ],
    "346cb205": [
      6
    ],
    "5ef0ed2a": [
      6
    ],
    "239a9ea7": [
      6
    ],
    "0b173c48": [
      6
    ],
    "6d4598fe": [
      51,
      10
    ],
    "c48c7066": [
      51,
      10
    ],
    "1015ab52": [
      51,
      10
    ],
    "87f8860c": [
      51,
      10
    ],
    "5dd19250": [
      51,
      10
    ],
    "415e7bcc": [
      6
    ],
    "6e8d4662": [
      6
    ],
    "0e9d8c46": [
      6
    ],
    "7bee75b4": [
      13,
      9,
      24,
      25,
      26,
      27,
      28,
      29,
      30,
      31,
      32,
      33,
      34,
      42,
      23,
      22,
      17,
      21,
      18,
      20,
      19,
      24,
      25,
      26,
      27,
      28,
      29,
      30,
      31,
      32,
      33,
      34,
      43,
      45
    ],
    "3c1e3e1f": [
      13,
      9,
      24,
      25,
      26,
      27,
      28,
      29,
      30,
      31,
      32,
      33,
      34,
      42,
      23,
      22,
      17,
      21,
      18,
      20,
      19,
      24,
      25,
      26,
      27,
      28,
      29,
      30,
      31,
      32,
      33,
      34,
      43,
      45
    ],
    "6c47186e": [
      13,
      9,
      24,
      25,
      26,
      27,
      28,
      29,
      30,
      31,
      32,
      33,
      34,
      42,
      23,
      22,
      17,
      21,
      18,
      20,
      19,
      24,
      25,
      26,
      27,
      28,
      29,
      30,
      31,
      32,
      33,
      34,
      43,
      45
    ],
    "792bddcc": [
      13,
      9,
      24,
      25,
      26,
      27,
      28,
      29,
      30,
      31,
      32,
      33,
      34,
      42,
      23,
      22,
      17,
      21,
      18,
      20,
      19,
      24,
      25,
      26,
      27,
      28,
      29,
      30,
      31,
      32,
      33,
      34,
      43,
      45
    ],
    "6c16d45d": [
      13,
      9,
      24,
      25,
      26,
      27,
      28,
      29,
      30,
      31,
      32,
      33,
      34,
      42,
      23,
      22,
      17,
      21,
      18,
      20,
      19,
      24,
      25,
      26,
      27,
      28,
      29,
      30,
      31,
      32,
      33,
      34,
      43,
      45
    ],
    "169281e5": [
      13,
      9,
      24,
      25,
      26,
      27,
      28,
      29,
      30,
      31,
      32,
      33,
      34,
      42,
      23,
      22,
      17,
      21,
      18,
      20,
      19,
      24,
      25,
      26,
      27,
      28,
      29,
      30,
      31,
      32,
      33,
      34,
      43,
      45
    ],
    "dc9fe026": [
      13,
      9,
      24,
      25,
      26,
      27,
      28,
      29,
      30,
      31,
      32,
      33,
      34,
      42,
      23,
      22,
      17,
      21,
      18,
      20,
      19,
      24,
      25,
      26,
      27,
      28,
      29,
      30,
      31,
      32,
      33,
      34,
      43,
      45
    ],
    "665e8dbf": [
      13,
      9,
      24,
      25,
      26,
      27,
      28,
      29,
      30,
      31,
      32,
      33,
      34,
      42,
      23,
      22,
      17,
      21,
      18,
      20,
      19,
      24,
      25,
      26,
      27,
      28,
      29,
      30,
      31,
      32,
      33,
      34,
      43,
      45
    ],
    "56f63f90": [
      13,
      9,
      24,
      25,
      26,
      27,
      28,
      29,
      30,
      31,
      32,
      33,
      34,
      42,
      23,
      22,
      17,
      21,
      18,
      20,
      19,
      24,
      25,
      26,
      27,
      28,
      29,
      30,
      31,
      32,
      33,
      34,
      43,
      45
    ],
    "23b2747c": [
      13,
      9,
      24,
      25,
      26,
      27,
      28,
      29,
      30,
      31,
      32,
      33,
      34,
      42,
      23,
      22,
      17,
      21,
      18,
      20,
      19,
      24,
      25,
      26,
      27,
      28,
      29,
      30,
      31,
      32,
      33,
      34,
      43,
      45
    ],
    "7f0bb3f2": [
      13,
      9,
      24,
      25,
      26,
      27,
      28,
      29,
      30,
      31,
      32,
      33,
      34,
      42,
      23,
      22,
      17,
      21,
      18,
      20,
      19,
      24,
      25,
      26,
      27,
      28,
      29,
      30,
      31,
      32,
      33,
      34,
      43,
      45
    ],
    "0b62be1f": [
      13,
      9,
      24,
      25,
      26,
      27,
      28,
      29,
      30,
      31,
      32,
      33,
      34,
      42,
      23,
      22,
      17,
      21,
      18,
      20,
      19,
      24,
      25,
      26,
      27,
      28,
      29,
      30,
      31,
      32,
      33,
      34,
      43,
      45
    ],
    "87eeaaac": [
      13,
      9,
      24,
      25,
      26,
      27,
      28,
      29,
      30,
      31,
      32,
      33,
      34,
      42,
      23,
      22,
      17,
      21,
      18,
      20,
      19,
      24,
      25,
      26,
      27,
      28,
      29,
      30,
      31,
      32,
      33,
      34,
      43,
      45
    ],
    "8f4f6368": [
      13,
      9,
      24,
      25,
      26,
      27,
      28,
      29,
      30,
      31,
      32,
      33,
      34,
      42,
      23,
      22,
      17,
      21,
      18,
      20,
      19,
      24,
      25,
      26,
      27,
      28,
      29,
      30,
      31,
      32,
      33,
      34,
      43,
      45
    ],
    "454d127a": [
      13,
      9,
      24,
      25,
      26,
      27,
      28,
      29,
      30,
      31,
      32,
      33,
      34,
      42,
      23,
      22,
      17,
      21,
      18,
      20,
      19,
      24,
      25,
      26,
      27,
      28,
      29,
      30,
      31,
      32,
      33,
      34,
      43,
      45
    ],
    "3c0b5f04": [
      13,
      9,
      24,
      25,
      26,
      27,
      28,
      29,
      30,
      31,
      32,
      33,
      34,
      42,
      23,
      22,
      17,
      21,
      18,
      20,
      19,
      24,
      25,
      26,
      27,
      28,
      29,
      30,
      31,
      32,
      33,
      34,
      43,
      45
    ],
    "3fe3f4eb": [
      13,
      9,
      24,
      25,
      26,
      27,
      28,
      29,
      30,
      31,
      32,
      33,
      34,
      42,
      23,
      22,
      17,
      21,
      18,
      20,
      19,
      24,
      25,
      26,
      27,
      28,
      29,
      30,
      31,
      32,
      33,
      34,
      43,
      45
    ],
    "1a4f9748": [
      13,
      9,
      24,
      25,
      26,
      27,
      28,
      29,
      30,
      31,
      32,
      33,
      34,
      42,
      23,
      22,
      17,
      21,
      18,
      20,
      19,
      24,
      25,
      26,
      27,
      28,
      29,
      30,
      31,
      32,
      33,
      34,
      43,
      45
    ],
    "a0d7b6fe": [
      13,
      9,
      24,
      25,
      26,
      27,
      28,
      29,
      30,
      31,
      32,
      33,
      34,
      42,
      23,
      22,
      17,
      21,
      18,
      20,
      19,
      24,
      25,
      26,
      27,
      28,
      29,
      30,
      31,
      32,
      33,
      34,
      43,
      45
    ],
    "b6552274": [
      13,
      9,
      24,
      25,
      26,
      27,
      28,
      29,
      30,
      31,
      32,
      33,
      34,
      42,
      23,
      22,
      17,
      21,
      18,
      20,
      19,
      24,
      25,
      26,
      27,
      28,
      29,
      30,
      31,
      32,
      33,
      34,
      43,
      45
    ],
    "623f28ec": [
      13,
      9,
      24,
      25,
      26,
      27,
      28,
      29,
      30,
      31,
      32,
      33,
      34,
      42,
      23,
      22,
      17,
      21,
      18,
      20,
      19,
      24,
      25,
      26,
      27,
      28,
      29,
      30,
      31,
      32,
      33,
      34,
      43,
      45
    ],
    "6811a4e4": [
      13,
      9,
      24,
      25,
      26,
      27,
      28,
      29,
      30,
      31,
      32,
      33,
      34,
      42,
      23,
      22,
      17,
      21,
      18,
      20,
      19,
      24,
      25,
      26,
      27,
      28,
      29,
      30,
      31,
      32,
      33,
      34,
      43,
      45
    ],
    "5f8a594e": [
      13,
      9,
      24,
      25,
      26,
      27,
      28,
      29,
      30,
      31,
      32,
      33,
      34,
      42,
      23,
      22,
      17,
      21,
      18,
      20,
      19,
      24,
      25,
      26,
      27,
      28,
      29,
      30,
      31,
      32,
      33,
      34,
      43,
      45
    ],
    "730c8b48": [
      6
    ],
    "2332c69b": [
      6
    ],
    "1bc82c66": [
      6
    ],
    "4985a098": [
      6
    ],
    "b0e03428": [
      6
    ],
    "5f9b762d": [
      6
    ],
    "6c35a9d8": [
      6
    ],
    "13bc3584": [
      6
    ],
    "5a14d3b7": [
      6
    ],
    "26a42502": [
      6
    ],
    "26be0384": [
      6
    ],
    "5001bb66": [
      6
    ],
    "b679dc46": [
      6
    ],
    "aeb360d4": [
      51,
      10
    ],
    "cb2592b4": [
      51,
      10
    ],
    "a3f4e0fc": [
      6
    ],
    "112c8146": [
      6
    ],
    "e520c63a": [
      6
    ],
    "335e21c2": [
      6
    ],
    "603e02da": [
      6
    ],
    "5aec976c": [
      6
    ],
    "3706e845": [
      6
    ],
    "6482dc20": [
      6
    ],
    "7d34dda5": [
      6
    ],
    "9fbeb2de": [
      6
    ],
    "236291f8": [
      6
    ],
    "274dc5a0": [
      6
    ],
    "25c91d3b": [
      6
    ],
    "8eb1c842": [
      13,
      9,
      24,
      25,
      26,
      27,
      28,
      29,
      30,
      31,
      32,
      33,
      34,
      42,
      23,
      22,
      17,
      21,
      18,
      20,
      19,
      24,
      25,
      26,
      27,
      28,
      29,
      30,
      31,
      32,
      33,
      34,
      43,
      45
    ],
    "0f61ee53": [
      51,
      10
    ],
    "038fef1d": [
      51,
      10
    ],
    "5d81b8ff": [
      6
    ],
    "d0393934": [
      6
    ],
    "2728e3b0": [
      6
    ],
    "317c57cc": [
      6
    ],
    "e3aadc3c": [
      6
    ],
    "3c3ae098": [
      6
    ],
    "019ac5de": [
      6
    ],
    "40aca382": [
      6
    ],
    "cfc6d1e2": [
      6
    ],
    "526ba07e": [
      6
    ],
    "6689d012": [
      6
    ],
    "3d77bdbe": [
      6
    ],
    "c6de6860": [
      6
    ],
    "0b44a6c3": [
      6
    ],
    "4093eef7": [
      6
    ],
    "407b62ed": [
      6
    ],
    "631a9f28": [
      13,
      9,
      24,
      25,
      26,
      27,
      28,
      29,
      30,
      31,
      32,
      33,
      34,
      42,
      23,
      22,
      17,
      21,
      18,
      20,
      19,
      24,
      25,
      26,
      27,
      28,
      29,
      30,
      31,
      32,
      33,
      34,
      43,
      45
    ],
    "77ed6474": [
      13,
      9,
      24,
      25,
      26,
      27,
      28,
      29,
      30,
      31,
      32,
      33,
      34,
      42,
      23,
      22,
      17,
      21,
      18,
      20,
      19,
      24,
      25,
      26,
      27,
      28,
      29,
      30,
      31,
      32,
      33,
      34,
      43,
      45
    ],
    "31c0e0a0": [
      13,
      9,
      24,
      25,
      26,
      27,
      28,
      29,
      30,
      31,
      32,
      33,
      34,
      42,
      23,
      22,
      17,
      21,
      18,
      20,
      19,
      24,
      25,
      26,
      27,
      28,
      29,
      30,
      31,
      32,
      33,
      34,
      43,
      45
    ],
    "d6cbd808": [
      13,
      9,
      24,
      25,
      26,
      27,
      28,
      29,
      30,
      31,
      32,
      33,
      34,
      42,
      23,
      22,
      17,
      21,
      18,
      20,
      19,
      24,
      25,
      26,
      27,
      28,
      29,
      30,
      31,
      32,
      33,
      34,
      43,
      45
    ],
    "d97bb188": [
      13,
      9,
      24,
      25,
      26,
      27,
      28,
      29,
      30,
      31,
      32,
      33,
      34,
      42,
      23,
      22,
      17,
      21,
      18,
      20,
      19,
      24,
      25,
      26,
      27,
      28,
      29,
      30,
      31,
      32,
      33,
      34,
      43,
      45
    ],
    "70351fe2": [
      13,
      9,
      24,
      25,
      26,
      27,
      28,
      29,
      30,
      31,
      32,
      33,
      34,
      42,
      23,
      22,
      17,
      21,
      18,
      20,
      19,
      24,
      25,
      26,
      27,
      28,
      29,
      30,
      31,
      32,
      33,
      34,
      43,
      45
    ],
    "54f7d110": [
      13,
      9,
      24,
      25,
      26,
      27,
      28,
      29,
      30,
      31,
      32,
      33,
      34,
      42,
      23,
      22,
      17,
      21,
      18,
      20,
      19,
      24,
      25,
      26,
      27,
      28,
      29,
      30,
      31,
      32,
      33,
      34,
      43,
      45
    ],
    "480e9363": [
      13,
      9,
      24,
      25,
      26,
      27,
      28,
      29,
      30,
      31,
      32,
      33,
      34,
      42,
      23,
      22,
      17,
      21,
      18,
      20,
      19,
      24,
      25,
      26,
      27,
      28,
      29,
      30,
      31,
      32,
      33,
      34,
      43,
      45
    ],
    "3874556c": [
      51,
      10
    ],
    "3873602b": [
      13,
      9,
      24,
      25,
      26,
      27,
      28,
      29,
      30,
      31,
      32,
      33,
      34,
      42,
      23,
      22,
      17,
      21,
      18,
      20,
      19,
      24,
      25,
      26,
      27,
      28,
      29,
      30,
      31,
      32,
      33,
      34,
      43,
      45
    ],
    "73c85780": [
      13,
      9,
      24,
      25,
      26,
      27,
      28,
      29,
      30,
      31,
      32,
      33,
      34,
      42,
      23,
      22,
      17,
      21,
      18,
      20,
      19,
      24,
      25,
      26,
      27,
      28,
      29,
      30,
      31,
      32,
      33,
      34,
      43,
      45
    ],
    "4f70d2b7": [
      13,
      9,
      24,
      25,
      26,
      27,
      28,
      29,
      30,
      31,
      32,
      33,
      34,
      42,
      23,
      22,
      17,
      21,
      18,
      20,
      19,
      24,
      25,
      26,
      27,
      28,
      29,
      30,
      31,
      32,
      33,
      34,
      43,
      45
    ],
    "25e9b95f": [
      13,
      9,
      24,
      25,
      26,
      27,
      28,
      29,
      30,
      31,
      32,
      33,
      34,
      42,
      23,
      22,
      17,
      21,
      18,
      20,
      19,
      24,
      25,
      26,
      27,
      28,
      29,
      30,
      31,
      32,
      33,
      34,
      43,
      45
    ],
    "528195a2": [
      13,
      9,
      24,
      25,
      26,
      27,
      28,
      29,
      30,
      31,
      32,
      33,
      34,
      42,
      23,
      22,
      17,
      21,
      18,
      20,
      19,
      24,
      25,
      26,
      27,
      28,
      29,
      30,
      31,
      32,
      33,
      34,
      43,
      45
    ],
    "8c7cd640": [
      13,
      9,
      24,
      25,
      26,
      27,
      28,
      29,
      30,
      31,
      32,
      33,
      34,
      42,
      23,
      22,
      17,
      21,
      18,
      20,
      19,
      24,
      25,
      26,
      27,
      28,
      29,
      30,
      31,
      32,
      33,
      34,
      43,
      45
    ],
    "08778e96": [
      6
    ],
    "70e84e0e": [
      6
    ],
    "31a6072a": [
      6
    ],
    "6e88c664": [
      6
    ],
    "a9e7495a": [
      6
    ],
    "2cde0a8e": [
      6
    ],
    "1d235f5d": [
      6
    ],
    "528910a7": [
      6
    ],
    "4910ac28": [
      6
    ],
    "252e23d7": [
      6
    ],
    "ce0c6904": [
      6
    ],
    "5ab36dc8": [
      6
    ],
    "f11cfd78": [
      6
    ],
    "286ec3b6": [
      6
    ],
    "2dd4b516": [
      6
    ],
    "aa88187e": [
      6
    ],
    "002b8509": [
      6
    ],
    "eb7cc02c": [
      6
    ],
    "1b9ab008": [
      6
    ],
    "fe1d8ae2": [
      6
    ],
    "0ecfce12": [
      6
    ],
    "674fa62d": [
      6
    ],
    "3b83527c": [
      6
    ],
    "868b914c": [
      6
    ],
    "ab4dff0e": [
      6
    ],
    "329a17ae": [
      6
    ],
    "37dfbab6": [
      13,
      9,
      24,
      25,
      26,
      27,
      28,
      29,
      30,
      31,
      32,
      33,
      34,
      42,
      23,
      22,
      17,
      21,
      18,
      20,
      19,
      24,
      25,
      26,
      27,
      28,
      29,
      30,
      31,
      32,
      33,
      34,
      43,
      45
    ],
    "3bd40338": [
      51,
      10
    ],
    "1725c507": [
      13,
      9,
      24,
      25,
      26,
      27,
      28,
      29,
      30,
      31,
      32,
      33,
      34,
      42,
      23,
      22,
      17,
      21,
      18,
      20,
      19,
      24,
      25,
      26,
      27,
      28,
      29,
      30,
      31,
      32,
      33,
      34,
      43,
      45
    ],
    "3424b997": [
      13,
      9,
      24,
      25,
      26,
      27,
      28,
      29,
      30,
      31,
      32,
      33,
      34,
      42,
      23,
      22,
      17,
      21,
      18,
      20,
      19,
      24,
      25,
      26,
      27,
      28,
      29,
      30,
      31,
      32,
      33,
      34,
      43,
      45
    ],
    "42bc1a1f": [
      13,
      9,
      24,
      25,
      26,
      27,
      28,
      29,
      30,
      31,
      32,
      33,
      34,
      42,
      23,
      22,
      17,
      21,
      18,
      20,
      19,
      24,
      25,
      26,
      27,
      28,
      29,
      30,
      31,
      32,
      33,
      34,
      43,
      45
    ],
    "224e3901": [
      6
    ],
    "3b2cb8ff": [
      6
    ],
    "9b6d8490": [
      6
    ],
    "3db71846": [
      6
    ],
    "4f5e0fd3": [
      6
    ],
    "026d02a0": [
      6
    ],
    "3f2864b2": [
      6
    ],
    "6f9112e6": [
      6
    ],
    "225c5308": [
      6
    ],
    "68f4b5c6": [
      6
    ],
    "8d49826e": [
      6
    ],
    "29bd4682": [
      6
    ],
    "256e43fb": [
      6
    ],
    "31ccbbaf": [
      6
    ],
    "04793f26": [
      6
    ],
    "640dbfc0": [
      6
    ],
    "391b241e": [
      6
    ],
    "de25691a": [
      6
    ],
    "2c4c7214": [
      6
    ],
    "758a8e5e": [
      6
    ],
    "f3307c42": [
      6
    ],
    "24edcf9b": [
      6
    ],
    "5ba2b7bd": [
      6
    ],
    "e369b880": [
      6
    ],
    "372e8fa2": [
      6
    ],
    "dfb1faf4": [
      6
    ],
    "09ca0376": [
      6
    ],
    "22ea4273": [
      6
    ],
    "649277fe": [
      6
    ],
    "50924dbc": [
      6
    ],
    "f51703be": [
      6
    ],
    "20e72a19": [
      6
    ],
    "75e730bf": [
      6
    ],
    "5e28df04": [
      6
    ],
    "1589c7ce": [
      6
    ],
    "cda2d940": [
      6
    ],
    "ae7d84d0": [
      6
    ],
    "af599d40": [
      6
    ],
    "0cd73e1c": [
      13,
      9,
      24,
      25,
      26,
      27,
      28,
      29,
      30,
      31,
      32,
      33,
      34,
      42,
      23,
      22,
      17,
      21,
      18,
      20,
      19,
      24,
      25,
      26,
      27,
      28,
      29,
      30,
      31,
      32,
      33,
      34,
      43,
      45
    ],
    "e3e37eec": [
      13,
      9,
      24,
      25,
      26,
      27,
      28,
      29,
      30,
      31,
      32,
      33,
      34,
      42,
      23,
      22,
      17,
      21,
      18,
      20,
      19,
      24,
      25,
      26,
      27,
      28,
      29,
      30,
      31,
      32,
      33,
      34,
      43,
      45
    ],
    "e3c74fea": [
      13,
      9,
      24,
      25,
      26,
      27,
      28,
      29,
      30,
      31,
      32,
      33,
      34,
      42,
      23,
      22,
      17,
      21,
      18,
      20,
      19,
      24,
      25,
      26,
      27,
      28,
      29,
      30,
      31,
      32,
      33,
      34,
      43,
      45
    ],
    "0ce5559d": [
      13,
      9,
      24,
      25,
      26,
      27,
      28,
      29,
      30,
      31,
      32,
      33,
      34,
      42,
      23,
      22,
      17,
      21,
      18,
      20,
      19,
      24,
      25,
      26,
      27,
      28,
      29,
      30,
      31,
      32,
      33,
      34,
      43,
      45
    ],
    "0cf36d1e": [
      13,
      9,
      24,
      25,
      26,
      27,
      28,
      29,
      30,
      31,
      32,
      33,
      34,
      42,
      23,
      22,
      17,
      21,
      18,
      20,
      19,
      24,
      25,
      26,
      27,
      28,
      29,
      30,
      31,
      32,
      33,
      34,
      43,
      45
    ],
    "0d01849f": [
      13,
      9,
      24,
      25,
      26,
      27,
      28,
      29,
      30,
      31,
      32,
      33,
      34,
      42,
      23,
      22,
      17,
      21,
      18,
      20,
      19,
      24,
      25,
      26,
      27,
      28,
      29,
      30,
      31,
      32,
      33,
      34,
      43,
      45
    ],
    "0d0f9c20": [
      13,
      9,
      24,
      25,
      26,
      27,
      28,
      29,
      30,
      31,
      32,
      33,
      34,
      42,
      23,
      22,
      17,
      21,
      18,
      20,
      19,
      24,
      25,
      26,
      27,
      28,
      29,
      30,
      31,
      32,
      33,
      34,
      43,
      45
    ],
    "0d1db3a1": [
      13,
      9,
      24,
      25,
      26,
      27,
      28,
      29,
      30,
      31,
      32,
      33,
      34,
      42,
      23,
      22,
      17,
      21,
      18,
      20,
      19,
      24,
      25,
      26,
      27,
      28,
      29,
      30,
      31,
      32,
      33,
      34,
      43,
      45
    ],
    "0d2bcb22": [
      13,
      9,
      24,
      25,
      26,
      27,
      28,
      29,
      30,
      31,
      32,
      33,
      34,
      42,
      23,
      22,
      17,
      21,
      18,
      20,
      19,
      24,
      25,
      26,
      27,
      28,
      29,
      30,
      31,
      32,
      33,
      34,
      43,
      45
    ],
    "0d39e2a3": [
      13,
      9,
      24,
      25,
      26,
      27,
      28,
      29,
      30,
      31,
      32,
      33,
      34,
      42,
      23,
      22,
      17,
      21,
      18,
      20,
      19,
      24,
      25,
      26,
      27,
      28,
      29,
      30,
      31,
      32,
      33,
      34,
      43,
      45
    ],
    "0d477e04": [
      13,
      9,
      24,
      25,
      26,
      27,
      28,
      29,
      30,
      31,
      32,
      33,
      34,
      42,
      23,
      22,
      17,
      21,
      18,
      20,
      19,
      24,
      25,
      26,
      27,
      28,
      29,
      30,
      31,
      32,
      33,
      34,
      43,
      45
    ],
    "7d903aba": [
      6
    ],
    "fb9578f8": [
      6
    ],
    "cd59f69c": [
      6
    ],
    "5265b192": [
      6
    ],
    "2e601b2e": [
      6
    ],
    "64b59322": [
      6
    ],
    "cbfc0598": [
      6
    ],
    "ab23ab48": [
      6
    ],
    "66abf1b7": [
      6
    ],
    "1f306fc9": [
      6
    ],
    "757ba0cc": [
      6
    ],
    "2c21ec57": [
      51,
      10
    ],
    "1114cea6": [
      6
    ],
    "1dbb507d": [
      51,
      10
    ],
    "5afc2509": [
      51,
      10
    ],
    "305a4846": [
      13,
      9,
      24,
      25,
      26,
      27,
      28,
      29,
      30,
      31,
      32,
      33,
      34,
      42,
      23,
      22,
      17,
      21,
      18,
      20,
      19,
      24,
      25,
      26,
      27,
      28,
      29,
      30,
      31,
      32,
      33,
      34,
      43,
      45
    ],
    "ce4af57e": [
      51,
      10
    ],
    "9d80f884": [
      51,
      10
    ],
    "aa1ef38c": [
      51,
      10
    ],
    "c4236d76": [
      51,
      10
    ],
    "4459ee0f": [
      51,
      10
    ],
    "647fd545": [
      51,
      10
    ],
    "5a7c2702": [
      51,
      10
    ],
    "08bb2c05": [
      51,
      10
    ],
    "a87932f6": [
      51,
      10
    ],
    "55e7cf7b": [
      51,
      10
    ],
    "65dd3440": [
      51,
      10
    ],
    "2e359c65": [
      51,
      10
    ],
    "3eb3cb9a": [
      51,
      10
    ],
    "408b5ec4": [
      51,
      10
    ],
    "bc046992": [
      51,
      10
    ],
    "28c37ba8": [
      51,
      10
    ],
    "b0c5ec6e": [
      51,
      10
    ],
    "bc12fbb6": [
      51,
      10
    ],
    "34d80634": [
      51,
      10
    ],
    "5ecd6ee5": [
      51,
      10
    ],
    "5d259dc5": [
      51,
      10
    ],
    "27130c9a": [
      51,
      10
    ],
    "1d92b376": [
      51,
      10
    ],
    "17e8bff7": [
      51,
      10
    ],
    "bc1132f6": [
      51,
      10
    ],
    "22ca5ad9": [
      51,
      10
    ],
    "6df5f4cc": [
      51,
      10
    ],
    "a2d045f2": [
      51,
      10
    ],
    "7072ccba": [
      51,
      10
    ],
    "6b7abaa2": [
      51,
      10
    ],
    "9f2b663e": [
      51,
      10
    ],
    "4945170f": [
      51,
      10
    ],
    "13d85376": [
      51,
      10
    ],
    "58110a2a": [
      51,
      10
    ],
    "3638f9c2": [
      51,
      10
    ],
    "5adf950e": [
      51,
      10
    ],
    "05e611c4": [
      51,
      10
    ],
    "18aa114f": [
      51,
      10
    ],
    "56a96c13": [
      51,
      10
    ],
    "58abfb72": [
      51,
      10
    ],
    "507a0f76": [
      51,
      10
    ],
    "22ee21a1": [
      51,
      10
    ],
    "b91e8a12": [
      51,
      10
    ],
    "8a9ed8d2": [
      51,
      10
    ],
    "35acada5": [
      51,
      10
    ],
    "8f55781e": [
      51,
      10
    ],
    "1449816c": [
      51,
      10
    ],
    "9236a5b6": [
      51,
      10
    ],
    "505c826e": [
      51,
      10
    ],
    "cfdbca34": [
      51,
      10
    ],
    "c0076062": [
      51,
      10
    ],
    "6b237559": [
      51,
      10
    ],
    "1ead15c5": [
      51,
      10
    ],
    "314e0378": [
      51,
      10
    ],
    "052c866f": [
      51,
      10
    ],
    "0b14ca1a": [
      51,
      10
    ],
    "2e434f66": [
      51,
      10
    ],
    "11a5646a": [
      51,
      10
    ],
    "61e9f59c": [
      51,
      10
    ],
    "0a9a1158": [
      51,
      10
    ],
    "7926fc62": [
      51,
      10
    ],
    "e90a53be": [
      51,
      10
    ],
    "ecd50c34": [
      51,
      10
    ],
    "99fee804": [
      51,
      10
    ],
    "bd01c9da": [
      51,
      10
    ],
    "66a472a5": [
      51,
      10
    ],
    "4a7e5185": [
      51,
      10
    ],
    "3dab4073": [
      51,
      10
    ],
    "405478bf": [
      51,
      10
    ],
    "1ae5be52": [
      51,
      10
    ],
    "23902ef3": [
      51,
      10
    ],
    "2371eab4": [
      51,
      10
    ],
    "cd15939a": [
      51,
      10
    ],
    "5fc217a6": [
      51,
      10
    ],
    "00a79702": [
      51,
      10
    ],
    "05e65c05": [
      51,
      10
    ],
    "50d4693e": [
      51,
      10
    ],
    "44eb34e5": [
      51,
      10
    ],
    "8bc6a314": [
      51,
      10
    ],
    "0b9a7753": [
      51,
      10
    ],
    "71c61965": [
      51,
      10
    ],
    "0875c5f1": [
      51,
      10
    ],
    "18ef9c65": [
      51,
      10
    ],
    "59a2e559": [
      51,
      10
    ],
    "326ddc27": [
      51,
      10
    ],
    "9373f61a": [
      51,
      10
    ],
    "694a73e6": [
      51,
      10
    ],
    "565db883": [
      51,
      10
    ],
    "82773d24": [
      51,
      10
    ],
    "2c915d02": [
      51,
      10
    ],
    "65b8bef9": [
      51,
      10
    ],
    "be280cae": [
      51,
      10
    ],
    "284e1d92": [
      51,
      10
    ],
    "085dd328": [
      51,
      10
    ],
    "7f855425": [
      51,
      10
    ],
    "7d482716": [
      51,
      10
    ],
    "8e51b4b2": [
      51,
      10
    ],
    "6ce35cf0": [
      51,
      10
    ],
    "3007100f": [
      51,
      10
    ],
    "7819941c": [
      51,
      10
    ],
    "02d39dc2": [
      51,
      10
    ],
    "de11a1b8": [
      51,
      10
    ],
    "f27ac0f6": [
      51,
      10
    ],
    "ca598da2": [
      51,
      10
    ],
    "0dc5d7de": [
      51,
      10
    ],
    "4c04b2b6": [
      51,
      10
    ],
    "1acfb282": [
      51,
      10
    ],
    "1949e5e5": [
      51,
      10
    ],
    "1590dc26": [
      51,
      10
    ],
    "637c96c6": [
      51,
      10
    ],
    "896cbf76": [
      51,
      10
    ],
    "5bb080ae": [
      51,
      10
    ],
    "ec608f72": [
      51,
      10
    ],
    "03cef0ca": [
      51,
      10
    ],
    "2d8156ac": [
      51,
      10
    ],
    "98d52f96": [
      51,
      10
    ],
    "200a3ef2": [
      51,
      10
    ],
    "256ef7ba": [
      51,
      10
    ],
    "a6e6e916": [
      51,
      10
    ],
    "320dedda": [
      51,
      10
    ],
    "191b67de": [
      51,
      10
    ],
    "2f482777": [
      51,
      10
    ],
    "3f103092": [
      51,
      10
    ],
    "0dd2af5d": [
      51,
      10
    ],
    "39f42c66": [
      51,
      10
    ],
    "4bed0c39": [
      51,
      10
    ],
    "0a7c80a8": [
      51,
      10
    ],
    "3fc5d445": [
      51,
      10
    ],
    "55ae07af": [
      51,
      10
    ],
    "26b3180b": [
      51,
      10
    ],
    "16d88288": [
      51,
      10
    ],
    "2221d872": [
      51,
      10
    ],
    "7bba758b": [
      51,
      10
    ],
    "80db4d46": [
      51,
      10
    ],
    "9583f9ca": [
      51,
      10
    ],
    "82059af6": [
      51,
      10
    ],
    "1dc0cf06": [
      51,
      10
    ],
    "0544cf76": [
      51,
      10
    ],
    "ead3a532": [
      51,
      10
    ],
    "29b2f992": [
      51,
      10
    ],
    "19b63173": [
      51,
      10
    ],
    "03bb8076": [
      51,
      10
    ],
    "08a19990": [
      51,
      10
    ],
    "05608f34": [
      51,
      10
    ],
    "a72e2fc2": [
      51,
      10
    ],
    "4fbf44b6": [
      51,
      10
    ],
    "3583f0ca": [
      51,
      10
    ],
    "9c2d2ce2": [
      51,
      10
    ],
    "2b7af9a5": [
      51,
      10
    ],
    "45d3d474": [
      51,
      10
    ],
    "4cde7ec6": [
      51,
      10
    ],
    "3f423f23": [
      51,
      10
    ],
    "65ab8a6f": [
      51,
      10
    ],
    "3b34a1c1": [
      51,
      10
    ],
    "3b2e448f": [
      51,
      10
    ],
    "1beca3ce": [
      51,
      10
    ],
    "3b30160b": [
      51,
      10
    ],
    "1e2ac91b": [
      51,
      10
    ],
    "b147d13e": [
      51,
      10
    ],
    "6e8c7a92": [
      51,
      10
    ],
    "a1d16664": [
      51,
      10
    ],
    "c099e878": [
      51,
      10
    ],
    "93e4b3c2": [
      51,
      10
    ],
    "21069eaa": [
      51,
      10
    ],
    "ba7ff11c": [
      51,
      10
    ],
    "66ba8985": [
      51,
      10
    ],
    "5e2610f6": [
      51,
      10
    ],
    "a74034ce": [
      51,
      10
    ],
    "1886e1ac": [
      51,
      10
    ],
    "f6c2d33c": [
      51,
      10
    ],
    "1ea1a7a2": [
      51,
      10
    ],
    "52f01dd3": [
      51,
      10
    ],
    "497715a4": [
      51,
      10
    ],
    "60dadcee": [
      51,
      10
    ],
    "302c6b9a": [
      51,
      10
    ],
    "31ccf0c8": [
      51,
      10
    ],
    "114959e2": [
      51,
      10
    ],
    "06d39181": [
      51,
      10
    ],
    "4f4121a0": [
      51,
      10
    ],
    "c8229c9e": [
      51,
      10
    ],
    "0e3dea4e": [
      51,
      10
    ],
    "4922580b": [
      51,
      10
    ],
    "5ec3bfe1": [
      51,
      10
    ],
    "2d5feb98": [
      51,
      10
    ],
    "3092bc8f": [
      51,
      10
    ],
    "239b2851": [
      51,
      10
    ],
    "b3a8a0dc": [
      51,
      10
    ],
    "7fa3bb52": [
      51,
      10
    ],
    "30ae14ca": [
      51,
      10
    ],
    "2087a7de": [
      51,
      10
    ],
    "351a6654": [
      51,
      10
    ],
    "6ac3e699": [
      51,
      10
    ],
    "dadd201c": [
      51,
      10
    ],
    "db9384ac": [
      51,
      10
    ],
    "5e0c0678": [
      51,
      10
    ],
    "acf81f0e": [
      51,
      10
    ],
    "2f4f5744": [
      51,
      10
    ],
    "1892a92e": [
      51,
      10
    ],
    "49eb9025": [
      51,
      10
    ],
    "aa450072": [
      51,
      10
    ],
    "3d3d65ff": [
      51,
      10
    ],
    "0e57c65c": [
      51,
      10
    ],
    "6d95b220": [
      51,
      10
    ],
    "1a50e3f5": [
      51,
      10
    ],
    "347d1532": [
      51,
      10
    ],
    "042a0eea": [
      51,
      10
    ],
    "4a72e7f7": [
      51,
      10
    ],
    "fd5d3c30": [
      51,
      10
    ],
    "5bcf4dae": [
      51,
      10
    ],
    "529143c7": [
      51,
      10
    ],
    "1b87d1c3": [
      51,
      10
    ],
    "31de1c06": [
      51,
      10
    ],
    "44dcd3f2": [
      51,
      10
    ],
    "408223d4": [
      51,
      10
    ],
    "ce450b36": [
      51,
      10
    ],
    "20ff4020": [
      51,
      10
    ],
    "b59020fc": [
      51,
      10
    ],
    "00b72716": [
      51,
      10
    ],
    "ac7d6be4": [
      51,
      10
    ],
    "0064c10e": [
      51,
      10
    ],
    "1caeedd6": [
      51,
      10
    ],
    "644eb964": [
      51,
      10
    ],
    "1951512d": [
      51,
      10
    ],
    "02007518": [
      51,
      10
    ],
    "0565cfbf": [
      51,
      10
    ],
    "640741a5": [
      51,
      10
    ],
    "399911d8": [
      51,
      10
    ],
    "20ea0bd4": [
      51,
      10
    ],
    "16bc67e2": [
      51,
      10
    ],
    "932f7d76": [
      51,
      10
    ],
    "42e7c13c": [
      51,
      10
    ],
    "5539ea0a": [
      51,
      10
    ],
    "19b5907e": [
      51,
      10
    ],
    "14edfc6c": [
      51,
      10
    ],
    "73ed1bca": [
      51,
      10
    ],
    "4df4d44b": [
      51,
      10
    ],
    "375cb076": [
      51,
      10
    ],
    "b4f0a134": [
      51,
      10
    ],
    "0360864f": [
      51,
      10
    ],
    "642c80ac": [
      51,
      10
    ],
    "040261dd": [
      51,
      10
    ],
    "02aec688": [
      51,
      10
    ],
    "f2b93834": [
      51,
      10
    ],
    "6ca51f71": [
      51,
      10
    ],
    "596fc945": [
      51,
      10
    ],
    "040638a0": [
      51,
      10
    ],
    "a985668c": [
      51,
      10
    ],
    "12f8fcdc": [
      51,
      10
    ],
    "0682692f": [
      51,
      10
    ],
    "1f1c5913": [
      51,
      10
    ],
    "c3d08f5a": [
      51,
      10
    ],
    "eeeb027a": [
      51,
      10
    ],
    "4e291ea2": [
      51,
      10
    ],
    "5da790a4": [
      51,
      10
    ],
    "546ac603": [
      51,
      10
    ],
    "3919c38c": [
      51,
      10
    ],
    "e98c9a86": [
      51,
      10
    ],
    "77c844f6": [
      51,
      10
    ],
    "40f522c8": [
      51,
      10
    ],
    "7a7cfb9c": [
      51,
      10
    ],
    "17fe2102": [
      51,
      10
    ],
    "4a17d6ea": [
      51,
      10
    ],
    "772e62c6": [
      51,
      10
    ],
    "5b3454ee": [
      51,
      10
    ],
    "691ffb2e": [
      51,
      10
    ],
    "2fbc86aa": [
      51,
      10
    ],
    "8a13ad8c": [
      51,
      10
    ],
    "dc5abbc8": [
      51,
      10
    ],
    "66044bd0": [
      51,
      10
    ],
    "841885c4": [
      51,
      10
    ],
    "1d84c2e0": [
      51,
      10
    ],
    "d39e9832": [
      51,
      10
    ],
    "c38d47c2": [
      51,
      10
    ],
    "dacdc82e": [
      51,
      10
    ],
    "07fad53e": [
      51,
      10
    ],
    "ed74558a": [
      51,
      10
    ],
    "4650c0fd": [
      51,
      10
    ],
    "1eaa1398": [
      51,
      10
    ],
    "dc71bf84": [
      51,
      10
    ],
    "bd0dec14": [
      51,
      10
    ],
    "5039eb73": [
      51,
      10
    ],
    "12ec93c8": [
      51,
      10
    ],
    "472e1ec1": [
      51,
      10
    ],
    "7d24d65c": [
      51,
      10
    ],
    "7c2907bc": [
      51,
      10
    ],
    "59f0cc7c": [
      51,
      10
    ],
    "42cf270f": [
      51,
      10
    ],
    "2120da97": [
      51,
      10
    ],
    "b3e4a27e": [
      51,
      10
    ],
    "6f78d558": [
      51,
      10
    ],
    "46ff5e14": [
      51,
      10
    ],
    "44c5450a": [
      51,
      10
    ],
    "fefac1e2": [
      51,
      10
    ],
    "49e227a6": [
      51,
      10
    ],
    "fc2444fa": [
      51,
      10
    ],
    "2b6db202": [
      51,
      10
    ],
    "1dfb31ef": [
      51,
      10
    ],
    "59bd884a": [
      51,
      10
    ],
    "955b12f0": [
      51,
      10
    ],
    "6a0b7e5e": [
      51,
      10
    ],
    "7f7dbb6c": [
      51,
      10
    ],
    "4a0e0237": [
      51,
      10
    ],
    "49522a78": [
      51,
      10
    ],
    "0d113a94": [
      13,
      9,
      24,
      25,
      26,
      27,
      28,
      29,
      30,
      31,
      32,
      33,
      34,
      42,
      23,
      22,
      17,
      21,
      18,
      20,
      19,
      24,
      25,
      26,
      27,
      28,
      29,
      30,
      31,
      32,
      33,
      34,
      43,
      45
    ],
    "18cc439a": [
      13,
      9,
      24,
      25,
      26,
      27,
      28,
      29,
      30,
      31,
      32,
      33,
      34,
      42,
      23,
      22,
      17,
      21,
      18,
      20,
      19,
      24,
      25,
      26,
      27,
      28,
      29,
      30,
      31,
      32,
      33,
      34,
      43,
      45
    ],
    "7a5694f5": [
      13,
      9,
      24,
      25,
      26,
      27,
      28,
      29,
      30,
      31,
      32,
      33,
      34,
      42,
      23,
      22,
      17,
      21,
      18,
      20,
      19,
      24,
      25,
      26,
      27,
      28,
      29,
      30,
      31,
      32,
      33,
      34,
      43,
      45
    ],
    "0df0d2bb": [
      13,
      9,
      24,
      25,
      26,
      27,
      28,
      29,
      30,
      31,
      32,
      33,
      34,
      42,
      23,
      22,
      17,
      21,
      18,
      20,
      19,
      24,
      25,
      26,
      27,
      28,
      29,
      30,
      31,
      32,
      33,
      34,
      43,
      45
    ],
    "7d4c3894": [
      13,
      9,
      24,
      25,
      26,
      27,
      28,
      29,
      30,
      31,
      32,
      33,
      34,
      42,
      23,
      22,
      17,
      21,
      18,
      20,
      19,
      24,
      25,
      26,
      27,
      28,
      29,
      30,
      31,
      32,
      33,
      34,
      43,
      45
    ],
    "d0210880": [
      13,
      9,
      24,
      25,
      26,
      27,
      28,
      29,
      30,
      31,
      32,
      33,
      34,
      42,
      23,
      22,
      17,
      21,
      18,
      20,
      19,
      24,
      25,
      26,
      27,
      28,
      29,
      30,
      31,
      32,
      33,
      34,
      43,
      45
    ],
    "69b4a188": [
      13,
      9,
      24,
      25,
      26,
      27,
      28,
      29,
      30,
      31,
      32,
      33,
      34,
      42,
      23,
      22,
      17,
      21,
      18,
      20,
      19,
      24,
      25,
      26,
      27,
      28,
      29,
      30,
      31,
      32,
      33,
      34,
      43,
      45
    ],
    "141308c2": [
      13,
      9,
      24,
      25,
      26,
      27,
      28,
      29,
      30,
      31,
      32,
      33,
      34,
      42,
      23,
      22,
      17,
      21,
      18,
      20,
      19,
      24,
      25,
      26,
      27,
      28,
      29,
      30,
      31,
      32,
      33,
      34,
      43,
      45
    ],
    "c8ad7c00": [
      13,
      9,
      24,
      25,
      26,
      27,
      28,
      29,
      30,
      31,
      32,
      33,
      34,
      42,
      23,
      22,
      17,
      21,
      18,
      20,
      19,
      24,
      25,
      26,
      27,
      28,
      29,
      30,
      31,
      32,
      33,
      34,
      43,
      45
    ],
    "8d3d7940": [
      13,
      9,
      24,
      25,
      26,
      27,
      28,
      29,
      30,
      31,
      32,
      33,
      34,
      42,
      23,
      22,
      17,
      21,
      18,
      20,
      19,
      24,
      25,
      26,
      27,
      28,
      29,
      30,
      31,
      32,
      33,
      34,
      43,
      45
    ],
    "7034ac5a": [
      13,
      9,
      24,
      25,
      26,
      27,
      28,
      29,
      30,
      31,
      32,
      33,
      34,
      42,
      23,
      22,
      17,
      21,
      18,
      20,
      19,
      24,
      25,
      26,
      27,
      28,
      29,
      30,
      31,
      32,
      33,
      34,
      43,
      45
    ],
    "4619d986": [
      13,
      9,
      24,
      25,
      26,
      27,
      28,
      29,
      30,
      31,
      32,
      33,
      34,
      42,
      23,
      22,
      17,
      21,
      18,
      20,
      19,
      24,
      25,
      26,
      27,
      28,
      29,
      30,
      31,
      32,
      33,
      34,
      43,
      45
    ],
    "50f97736": [
      51,
      10
    ],
    "7ed70b46": [
      13,
      9,
      24,
      25,
      26,
      27,
      28,
      29,
      30,
      31,
      32,
      33,
      34,
      42,
      23,
      22,
      17,
      21,
      18,
      20,
      19,
      24,
      25,
      26,
      27,
      28,
      29,
      30,
      31,
      32,
      33,
      34,
      43,
      45
    ],
    "cb68c8ce": [
      6
    ],
    "324e7a7e": [
      6
    ],
    "61f781fa": [
      6
    ],
    "704eb43a": [
      6
    ],
    "4078afea": [
      6
    ],
    "5431abb4": [
      6
    ],
    "7e3345ce": [
      6
    ],
    "308f9cd6": [
      6
    ],
    "28c7f73e": [
      6
    ],
    "8efe8108": [
      6
    ],
    "16f7bb8d": [
      6
    ],
    "b779f58e": [
      6
    ],
    "cc1fb996": [
      6
    ],
    "39f667ea": [
      6
    ],
    "e86062ce": [
      6
    ],
    "2cd04119": [
      6
    ],
    "398eb37e": [
      6
    ],
    "4ce125c7": [
      6
    ],
    "65c7a39e": [
      6
    ],
    "e52a43fe": [
      6
    ],
    "29b0f162": [
      6
    ],
    "c0c95880": [
      13,
      9,
      24,
      25,
      26,
      27,
      28,
      29,
      30,
      31,
      32,
      33,
      34,
      42,
      23,
      22,
      17,
      21,
      18,
      20,
      19,
      24,
      25,
      26,
      27,
      28,
      29,
      30,
      31,
      32,
      33,
      34,
      43,
      45
    ],
    "d1d959e8": [
      13,
      9,
      24,
      25,
      26,
      27,
      28,
      29,
      30,
      31,
      32,
      33,
      34,
      42,
      23,
      22,
      17,
      21,
      18,
      20,
      19,
      24,
      25,
      26,
      27,
      28,
      29,
      30,
      31,
      32,
      33,
      34,
      43,
      45
    ],
    "5926d863": [
      51,
      10
    ],
    "25b9255c": [
      51,
      10
    ],
    "209a2614": [
      13,
      9,
      24,
      25,
      26,
      27,
      28,
      29,
      30,
      31,
      32,
      33,
      34,
      42,
      23,
      22,
      17,
      21,
      18,
      20,
      19,
      24,
      25,
      26,
      27,
      28,
      29,
      30,
      31,
      32,
      33,
      34,
      43,
      45
    ],
    "8da6234a": [
      13,
      9,
      24,
      25,
      26,
      27,
      28,
      29,
      30,
      31,
      32,
      33,
      34,
      42,
      23,
      22,
      17,
      21,
      18,
      20,
      19,
      24,
      25,
      26,
      27,
      28,
      29,
      30,
      31,
      32,
      33,
      34,
      43,
      45
    ],
    "1620888f": [
      13,
      9,
      24,
      25,
      26,
      27,
      28,
      29,
      30,
      31,
      32,
      33,
      34,
      42,
      23,
      22,
      17,
      21,
      18,
      20,
      19,
      24,
      25,
      26,
      27,
      28,
      29,
      30,
      31,
      32,
      33,
      34,
      43,
      45
    ],
    "7206b5c7": [
      13,
      9,
      24,
      25,
      26,
      27,
      28,
      29,
      30,
      31,
      32,
      33,
      34,
      42,
      23,
      22,
      17,
      21,
      18,
      20,
      19,
      24,
      25,
      26,
      27,
      28,
      29,
      30,
      31,
      32,
      33,
      34,
      43,
      45
    ],
    "7214cd48": [
      13,
      9,
      24,
      25,
      26,
      27,
      28,
      29,
      30,
      31,
      32,
      33,
      34,
      42,
      23,
      22,
      17,
      21,
      18,
      20,
      19,
      24,
      25,
      26,
      27,
      28,
      29,
      30,
      31,
      32,
      33,
      34,
      43,
      45
    ],
    "7222e4c9": [
      13,
      9,
      24,
      25,
      26,
      27,
      28,
      29,
      30,
      31,
      32,
      33,
      34,
      42,
      23,
      22,
      17,
      21,
      18,
      20,
      19,
      24,
      25,
      26,
      27,
      28,
      29,
      30,
      31,
      32,
      33,
      34,
      43,
      45
    ],
    "7230fc4a": [
      13,
      9,
      24,
      25,
      26,
      27,
      28,
      29,
      30,
      31,
      32,
      33,
      34,
      42,
      23,
      22,
      17,
      21,
      18,
      20,
      19,
      24,
      25,
      26,
      27,
      28,
      29,
      30,
      31,
      32,
      33,
      34,
      43,
      45
    ],
    "723f13cb": [
      13,
      9,
      24,
      25,
      26,
      27,
      28,
      29,
      30,
      31,
      32,
      33,
      34,
      42,
      23,
      22,
      17,
      21,
      18,
      20,
      19,
      24,
      25,
      26,
      27,
      28,
      29,
      30,
      31,
      32,
      33,
      34,
      43,
      45
    ],
    "724d2b4c": [
      13,
      9,
      24,
      25,
      26,
      27,
      28,
      29,
      30,
      31,
      32,
      33,
      34,
      42,
      23,
      22,
      17,
      21,
      18,
      20,
      19,
      24,
      25,
      26,
      27,
      28,
      29,
      30,
      31,
      32,
      33,
      34,
      43,
      45
    ],
    "725b42cd": [
      13,
      9,
      24,
      25,
      26,
      27,
      28,
      29,
      30,
      31,
      32,
      33,
      34,
      42,
      23,
      22,
      17,
      21,
      18,
      20,
      19,
      24,
      25,
      26,
      27,
      28,
      29,
      30,
      31,
      32,
      33,
      34,
      43,
      45
    ],
    "72695a4e": [
      13,
      9,
      24,
      25,
      26,
      27,
      28,
      29,
      30,
      31,
      32,
      33,
      34,
      42,
      23,
      22,
      17,
      21,
      18,
      20,
      19,
      24,
      25,
      26,
      27,
      28,
      29,
      30,
      31,
      32,
      33,
      34,
      43,
      45
    ],
    "7276f5af": [
      13,
      9,
      24,
      25,
      26,
      27,
      28,
      29,
      30,
      31,
      32,
      33,
      34,
      42,
      23,
      22,
      17,
      21,
      18,
      20,
      19,
      24,
      25,
      26,
      27,
      28,
      29,
      30,
      31,
      32,
      33,
      34,
      43,
      45
    ],
    "af6fc2ba": [
      13,
      9,
      24,
      25,
      26,
      27,
      28,
      29,
      30,
      31,
      32,
      33,
      34,
      42,
      23,
      22,
      17,
      21,
      18,
      20,
      19,
      24,
      25,
      26,
      27,
      28,
      29,
      30,
      31,
      32,
      33,
      34,
      43,
      45
    ],
    "5c9b8738": [
      13,
      9,
      24,
      25,
      26,
      27,
      28,
      29,
      30,
      31,
      32,
      33,
      34,
      42,
      23,
      22,
      17,
      21,
      18,
      20,
      19,
      24,
      25,
      26,
      27,
      28,
      29,
      30,
      31,
      32,
      33,
      34,
      43,
      45
    ],
    "53fd4574": [
      13,
      9,
      24,
      25,
      26,
      27,
      28,
      29,
      30,
      31,
      32,
      33,
      34,
      42,
      23,
      22,
      17,
      21,
      18,
      20,
      19,
      24,
      25,
      26,
      27,
      28,
      29,
      30,
      31,
      32,
      33,
      34,
      43,
      45
    ],
    "2a1c54b8": [
      13,
      9,
      24,
      25,
      26,
      27,
      28,
      29,
      30,
      31,
      32,
      33,
      34,
      42,
      23,
      22,
      17,
      21,
      18,
      20,
      19,
      24,
      25,
      26,
      27,
      28,
      29,
      30,
      31,
      32,
      33,
      34,
      43,
      45
    ],
    "5629f66a": [
      13,
      9,
      24,
      25,
      26,
      27,
      28,
      29,
      30,
      31,
      32,
      33,
      34,
      42,
      23,
      22,
      17,
      21,
      18,
      20,
      19,
      24,
      25,
      26,
      27,
      28,
      29,
      30,
      31,
      32,
      33,
      34,
      43,
      45
    ],
    "1a4bd36c": [
      13,
      9,
      24,
      25,
      26,
      27,
      28,
      29,
      30,
      31,
      32,
      33,
      34,
      42,
      23,
      22,
      17,
      21,
      18,
      20,
      19,
      24,
      25,
      26,
      27,
      28,
      29,
      30,
      31,
      32,
      33,
      34,
      43,
      45
    ],
    "b10423e0": [
      13,
      9,
      24,
      25,
      26,
      27,
      28,
      29,
      30,
      31,
      32,
      33,
      34,
      42,
      23,
      22,
      17,
      21,
      18,
      20,
      19,
      24,
      25,
      26,
      27,
      28,
      29,
      30,
      31,
      32,
      33,
      34,
      43,
      45
    ],
    "2b3d2ffb": [
      13,
      9,
      24,
      25,
      26,
      27,
      28,
      29,
      30,
      31,
      32,
      33,
      34,
      42,
      23,
      22,
      17,
      21,
      18,
      20,
      19,
      24,
      25,
      26,
      27,
      28,
      29,
      30,
      31,
      32,
      33,
      34,
      43,
      45
    ],
    "af6806b8": [
      6
    ],
    "7616d163": [
      6
    ],
    "7e03f6d7": [
      6
    ],
    "c9044768": [
      6
    ],
    "8cb4dcfe": [
      6
    ],
    "6bf0bb70": [
      6
    ],
    "4ce31a31": [
      6
    ],
    "dcfbcd8c": [
      6
    ],
    "4c52f7a0": [
      6
    ],
    "6b995114": [
      6
    ],
    "31a8a55c": [
      6
    ],
    "2461448d": [
      6
    ],
    "51779fe3": [
      6
    ],
    "23b280ce": [
      6
    ],
    "cd51e0a6": [
      6
    ],
    "541cda3a": [
      6
    ],
    "14de30c0": [
      6
    ],
    "4bb73b91": [
      6
    ],
    "54ac1510": [
      6
    ],
    "3f9bc181": [
      6
    ],
    "5c0ed051": [
      6
    ],
    "6853105c": [
      6
    ],
    "2e6bb0bc": [
      6
    ],
    "7a8c2124": [
      6
    ],
    "e227e86e": [
      6
    ],
    "50e81ac8": [
      6
    ],
    "00e16b84": [
      13,
      9,
      24,
      25,
      26,
      27,
      28,
      29,
      30,
      31,
      32,
      33,
      34,
      42,
      23,
      22,
      17,
      21,
      18,
      20,
      19,
      24,
      25,
      26,
      27,
      28,
      29,
      30,
      31,
      32,
      33,
      34,
      43,
      45
    ],
    "8cb6d90c": [
      13,
      9,
      24,
      25,
      26,
      27,
      28,
      29,
      30,
      31,
      32,
      33,
      34,
      42,
      23,
      22,
      17,
      21,
      18,
      20,
      19,
      24,
      25,
      26,
      27,
      28,
      29,
      30,
      31,
      32,
      33,
      34,
      43,
      45
    ],
    "50b3850d": [
      13,
      9,
      24,
      25,
      26,
      27,
      28,
      29,
      30,
      31,
      32,
      33,
      34,
      42,
      23,
      22,
      17,
      21,
      18,
      20,
      19,
      24,
      25,
      26,
      27,
      28,
      29,
      30,
      31,
      32,
      33,
      34,
      43,
      45
    ],
    "581deab6": [
      13,
      9,
      24,
      25,
      26,
      27,
      28,
      29,
      30,
      31,
      32,
      33,
      34,
      42,
      23,
      22,
      17,
      21,
      18,
      20,
      19,
      24,
      25,
      26,
      27,
      28,
      29,
      30,
      31,
      32,
      33,
      34,
      43,
      45
    ],
    "48e9f385": [
      13,
      9,
      24,
      25,
      26,
      27,
      28,
      29,
      30,
      31,
      32,
      33,
      34,
      42,
      23,
      22,
      17,
      21,
      18,
      20,
      19,
      24,
      25,
      26,
      27,
      28,
      29,
      30,
      31,
      32,
      33,
      34,
      43,
      45
    ],
    "67c8e626": [
      13,
      9,
      24,
      25,
      26,
      27,
      28,
      29,
      30,
      31,
      32,
      33,
      34,
      42,
      23,
      22,
      17,
      21,
      18,
      20,
      19,
      24,
      25,
      26,
      27,
      28,
      29,
      30,
      31,
      32,
      33,
      34,
      43,
      45
    ],
    "64bbd15d": [
      13,
      9,
      24,
      25,
      26,
      27,
      28,
      29,
      30,
      31,
      32,
      33,
      34,
      42,
      23,
      22,
      17,
      21,
      18,
      20,
      19,
      24,
      25,
      26,
      27,
      28,
      29,
      30,
      31,
      32,
      33,
      34,
      43,
      45
    ],
    "0ca6d3c0": [
      13,
      9,
      24,
      25,
      26,
      27,
      28,
      29,
      30,
      31,
      32,
      33,
      34,
      42,
      23,
      22,
      17,
      21,
      18,
      20,
      19,
      24,
      25,
      26,
      27,
      28,
      29,
      30,
      31,
      32,
      33,
      34,
      43,
      45
    ],
    "73694bae": [
      13,
      9,
      24,
      25,
      26,
      27,
      28,
      29,
      30,
      31,
      32,
      33,
      34,
      42,
      23,
      22,
      17,
      21,
      18,
      20,
      19,
      24,
      25,
      26,
      27,
      28,
      29,
      30,
      31,
      32,
      33,
      34,
      43,
      45
    ],
    "123278a8": [
      13,
      9,
      24,
      25,
      26,
      27,
      28,
      29,
      30,
      31,
      32,
      33,
      34,
      42,
      23,
      22,
      17,
      21,
      18,
      20,
      19,
      24,
      25,
      26,
      27,
      28,
      29,
      30,
      31,
      32,
      33,
      34,
      43,
      45
    ],
    "1d577c0d": [
      13,
      9,
      24,
      25,
      26,
      27,
      28,
      29,
      30,
      31,
      32,
      33,
      34,
      42,
      23,
      22,
      17,
      21,
      18,
      20,
      19,
      24,
      25,
      26,
      27,
      28,
      29,
      30,
      31,
      32,
      33,
      34,
      43,
      45
    ],
    "b0ebf0b0": [
      46,
      4
    ],
    "1491f412": [
      47,
      5
    ],
    "04cb9ffa": [
      50,
      3,
      37,
      38
    ],
    "31d3115b": [
      48,
      15,
      41
    ],
    "30820deb": [
      49,
      12,
      44,
      36,
      39,
      40,
      35
    ],
    "3798b9be": [
      49,
      12,
      44,
      36,
      39,
      40,
      35
    ],
    "72a01380": [
      46,
      4
    ],
    "6827d27a": [
      47,
      5
    ],
    "753726b8": [
      50,
      3,
      37,
      38
    ],
    "76ebff57": [
      50,
      3,
      37,
      38
    ],
    "6b38f73c": [
      50,
      3,
      37,
      38
    ],
    "70d5b0f6": [
      48,
      15,
      41
    ],
    "2f4fdbf3": [
      48,
      15,
      41
    ],
    "51f093b0": [
      49,
      12,
      44,
      36,
      39,
      40,
      35
    ],
    "0eedcfa7": [
      49,
      12,
      44,
      36,
      39,
      40,
      35
    ],
    "0195bf44": [
      49,
      12,
      44,
      36,
      39,
      40,
      35
    ],
    "33eb430f": [
      49,
      12,
      44,
      36,
      39,
      40,
      35
    ],
    "5e74642c": [
      49,
      12,
      44,
      36,
      39,
      40,
      35
    ],
    "7c12dafa": [
      49,
      12,
      44,
      36,
      39,
      40,
      35
    ],
    "37d2f056": [
      49,
      12,
      44,
      36,
      39,
      40,
      35
    ],
    "f7224514": [
      49,
      12,
      44,
      36,
      39,
      40,
      35
    ],
    "12a24faa": [
      49,
      12,
      44,
      36,
      39,
      40,
      35
    ],
    "57dab235": [
      49,
      12,
      44,
      36,
      39,
      40,
      35
    ],
    "2cf94432": [
      49,
      12,
      44,
      36,
      39,
      40,
      35
    ],
    "5ad055d4": [
      49,
      12,
      44,
      36,
      39,
      40,
      35
    ],
    "df058e8a": [
      49,
      12,
      44,
      36,
      39,
      40,
      35
    ],
    "7af9cc1c": [
      49,
      12,
      44,
      36,
      39,
      40,
      35
    ],
    "3cf4d0db": [
      49,
      12,
      44,
      36,
      39,
      40,
      35
    ],
    "6cd8a6a4": [
      49,
      12,
      44,
      36,
      39,
      40,
      35
    ],
    "02a3c88c": [
      49,
      12,
      44,
      36,
      39,
      40,
      35
    ],
    "64b702b1": [
      46,
      4
    ],
    "1f287ad3": [
      46,
      4
    ],
    "a2a7554c": [
      46,
      4
    ],
    "004ce35b": [
      46,
      4
    ],
    "9cbc0e0e": [
      46,
      4
    ],
    "80295cf2": [
      2
    ],
    "4ed7ff54": [
      2
    ],
    "1985f4c4": [
      2
    ],
    "098ce9dc": [
      2
    ],
    "7a7df423": [
      2
    ],
    "3cab0b02": [
      47,
      5
    ],
    "1c2f6f86": [
      47,
      5
    ],
    "7d92e0f7": [
      47,
      5
    ],
    "4b9147f2": [
      47,
      5
    ],
    "157deec4": [
      7
    ],
    "122f2a28": [
      7
    ],
    "2094d174": [
      7
    ],
    "835f7a8e": [
      50,
      3,
      37,
      38
    ],
    "a3bf2b52": [
      50,
      3,
      37,
      38
    ],
    "1cedda62": [
      50,
      3,
      37,
      38
    ],
    "03849a34": [
      48,
      15,
      41
    ],
    "2539c75a": [
      48,
      15,
      41
    ],
    "609da3e2": [
      48,
      15,
      41
    ],
    "76921a71": [
      8
    ],
    "210a15fa": [
      8
    ],
    "32e39d7b": [
      8
    ],
    "0ef42cba": [
      16
    ],
    "23c10497": [
      16
    ],
    "d8242dc2": [
      16
    ],
    "ec98d3ce": [
      51,
      10
    ],
    "de6da0c0": [
      51,
      10
    ],
    "5dc02112": [
      13,
      9,
      24,
      25,
      26,
      27,
      28,
      29,
      30,
      31,
      32,
      33,
      34,
      42,
      23,
      22,
      17,
      21,
      18,
      20,
      19,
      24,
      25,
      26,
      27,
      28,
      29,
      30,
      31,
      32,
      33,
      34,
      43,
      45
    ],
    "6466add4": [
      13,
      9,
      24,
      25,
      26,
      27,
      28,
      29,
      30,
      31,
      32,
      33,
      34,
      42,
      23,
      22,
      17,
      21,
      18,
      20,
      19,
      24,
      25,
      26,
      27,
      28,
      29,
      30,
      31,
      32,
      33,
      34,
      43,
      45
    ],
    "5c0d950b": [
      13,
      9,
      24,
      25,
      26,
      27,
      28,
      29,
      30,
      31,
      32,
      33,
      34,
      42,
      23,
      22,
      17,
      21,
      18,
      20,
      19,
      24,
      25,
      26,
      27,
      28,
      29,
      30,
      31,
      32,
      33,
      34,
      43,
      45
    ],
    "000b24d2": [
      13,
      9,
      24,
      25,
      26,
      27,
      28,
      29,
      30,
      31,
      32,
      33,
      34,
      42,
      23,
      22,
      17,
      21,
      18,
      20,
      19,
      24,
      25,
      26,
      27,
      28,
      29,
      30,
      31,
      32,
      33,
      34,
      43,
      45
    ],
    "2f9710cb": [
      46,
      4
    ],
    "39fdba8f": [
      47,
      5
    ],
    "45847dfe": [
      48,
      15,
      41
    ],
    "a41d883e": [
      49,
      12,
      44,
      36,
      39,
      40,
      35
    ],
    "7e5fbb37": [
      50,
      3,
      37,
      38
    ],
    "25eaf646": [
      13,
      9,
      24,
      25,
      26,
      27,
      28,
      29,
      30,
      31,
      32,
      33,
      34,
      42,
      23,
      22,
      17,
      21,
      18,
      20,
      19,
      24,
      25,
      26,
      27,
      28,
      29,
      30,
      31,
      32,
      33,
      34,
      43,
      45
    ],
    "567c87b9": [
      13,
      9,
      24,
      25,
      26,
      27,
      28,
      29,
      30,
      31,
      32,
      33,
      34,
      42,
      23,
      22,
      17,
      21,
      18,
      20,
      19,
      24,
      25,
      26,
      27,
      28,
      29,
      30,
      31,
      32,
      33,
      34,
      43,
      45
    ],
    "4de5195f": [
      13,
      9,
      24,
      25,
      26,
      27,
      28,
      29,
      30,
      31,
      32,
      33,
      34,
      42,
      23,
      22,
      17,
      21,
      18,
      20,
      19,
      24,
      25,
      26,
      27,
      28,
      29,
      30,
      31,
      32,
      33,
      34,
      43,
      45
    ],
    "66fc6fb9": [
      13,
      9,
      24,
      25,
      26,
      27,
      28,
      29,
      30,
      31,
      32,
      33,
      34,
      42,
      23,
      22,
      17,
      21,
      18,
      20,
      19,
      24,
      25,
      26,
      27,
      28,
      29,
      30,
      31,
      32,
      33,
      34,
      43,
      45
    ],
    "1d8addce": [
      49,
      12,
      44,
      36,
      39,
      40,
      35
    ],
    "a45964ca": [
      13,
      9,
      24,
      25,
      26,
      27,
      28,
      29,
      30,
      31,
      32,
      33,
      34,
      42,
      23,
      22,
      17,
      21,
      18,
      20,
      19,
      24,
      25,
      26,
      27,
      28,
      29,
      30,
      31,
      32,
      33,
      34,
      43,
      45
    ]
  },
  "assetsMapping": {
    "587c633c": [
      "0d369ea.js"
    ],
    "fa870064": [
      "0fc8ade.js"
    ],
    "2aff1868": [
      "1acdda1.js"
    ],
    "b70e4c64": [
      "1c1d6d6.js"
    ],
    "085a35c4": [
      "261c78a.js"
    ],
    "67c13ec2": [
      "45f6f75.js"
    ],
    "029af7da": [
      "5b75c0b.js"
    ],
    "1a3ae26b": [
      "6183672.js"
    ],
    "7ea24c87": [
      "86db296.js"
    ],
    "2a130dde": [
      "ac6bae7.js"
    ],
    "6fca0322": [
      "b4bc153.js"
    ],
    "4a45eea2": [
      "c3f605a.js"
    ],
    "a3834ade": [
      "faa11c8.js"
    ]
  }
}